{
	"name": "btnswitch",
	"plugin-id": "Sprite",
	"sid": 932129837096916,
	"isGlobal": false,
	"instanceVariables": [],
	"behaviorTypes": [
		{
			"behaviorId": "Tween",
			"name": "Tween",
			"sid": 330619564503966
		}
	],
	"effectTypes": [],
	"animations": {
		"items": [
			{
				"frames": [
					{
						"width": 615,
						"height": 815,
						"originX": 0.5,
						"originY": 0.5,
						"originalSource": "",
						"exportFormat": "png",
						"exportQuality": 0.8,
						"imageSpriteId": 7839789,
						"collisionPoly": {
							"points": [
								0.03902439024390244,
								0.0392638036809816,
								0.9609756097560975,
								0.0392638036809816,
								0.9609756097560975,
								0.9607361963190184,
								0.03902439024390244,
								0.9607361963190184
							]
						},
						"useCollisionPoly": true,
						"duration": 1
					}
				],
				"sid": 220253060297603,
				"name": "Default",
				"isLooping": false,
				"isPingPong": false,
				"repeatCount": 1,
				"repeatTo": 0,
				"speed": 5
			}
		],
		"subfolders": []
	}
}